openjd/adaptor_runtime/__init__.py
openjd/adaptor_runtime/_entrypoint.py
openjd/adaptor_runtime/_osname.py
openjd/adaptor_runtime/_version.py
openjd/adaptor_runtime/configuration.json
openjd/adaptor_runtime/configuration.schema.json
openjd/adaptor_runtime/py.typed
openjd/adaptor_runtime/_background/__init__.py
openjd/adaptor_runtime/_background/backend_named_pipe_server.py
openjd/adaptor_runtime/_background/backend_runner.py
openjd/adaptor_runtime/_background/background_named_pipe_request_handler.py
openjd/adaptor_runtime/_background/frontend_runner.py
openjd/adaptor_runtime/_background/http_server.py
openjd/adaptor_runtime/_background/loaders.py
openjd/adaptor_runtime/_background/log_buffers.py
openjd/adaptor_runtime/_background/model.py
openjd/adaptor_runtime/_background/server_response.py
openjd/adaptor_runtime/_http/__init__.py
openjd/adaptor_runtime/_http/exceptions.py
openjd/adaptor_runtime/_http/request_handler.py
openjd/adaptor_runtime/_http/sockets.py
openjd/adaptor_runtime/_named_pipe/__init__.py
openjd/adaptor_runtime/_named_pipe/named_pipe_request_handler.py
openjd/adaptor_runtime/_named_pipe/named_pipe_server.py
openjd/adaptor_runtime/_utils/__init__.py
openjd/adaptor_runtime/_utils/_constants.py
openjd/adaptor_runtime/_utils/_logging.py
openjd/adaptor_runtime/_utils/_secure_open.py
openjd/adaptor_runtime/adaptors/__init__.py
openjd/adaptor_runtime/adaptors/_adaptor.py
openjd/adaptor_runtime/adaptors/_adaptor_runner.py
openjd/adaptor_runtime/adaptors/_adaptor_states.py
openjd/adaptor_runtime/adaptors/_base_adaptor.py
openjd/adaptor_runtime/adaptors/_command_adaptor.py
openjd/adaptor_runtime/adaptors/_path_mapping.py
openjd/adaptor_runtime/adaptors/_validator.py
openjd/adaptor_runtime/adaptors/_versioning.py
openjd/adaptor_runtime/adaptors/configuration/__init__.py
openjd/adaptor_runtime/adaptors/configuration/_adaptor_configuration.schema.json
openjd/adaptor_runtime/adaptors/configuration/_configuration.py
openjd_adaptor_runtime-0.9.3.dist-info/METADATA
openjd_adaptor_runtime-0.9.3.dist-info/WHEEL
openjd_adaptor_runtime-0.9.3.dist-info/licenses/LICENSE
openjd_adaptor_runtime-0.9.3.dist-info/licenses/NOTICE
openjd_adaptor_runtime-0.9.3.dist-info/RECORD
