Metadata-Version: 2.4
Name: openjd-adaptor-runtime
Version: 0.9.3
Summary: A python library for building adaptors that integrate applications with Open Job Description jobs.
Project-URL: Homepage, https://github.com/OpenJobDescription/openjd-adaptor-runtime-for-python
Project-URL: Source, https://github.com/OpenJobDescription/openjd-adaptor-runtime-for-python
Author: Amazon Web Services
License-Expression: Apache-2.0
License-File: LICENSE
License-File: NOTICE
Classifier: Development Status :: 5 - Production/Stable
Classifier: Intended Audience :: Developers
Classifier: License :: OSI Approved :: Apache Software License
Classifier: Operating System :: MacOS
Classifier: Operating System :: Microsoft :: Windows
Classifier: Operating System :: POSIX :: Linux
Classifier: Programming Language :: Python
Classifier: Programming Language :: Python :: 3 :: Only
Classifier: Programming Language :: Python :: 3.9
Classifier: Programming Language :: Python :: 3.10
Classifier: Programming Language :: Python :: 3.11
Classifier: Programming Language :: Python :: 3.12
Requires-Python: >=3.9
Requires-Dist: jsonschema==4.*,>=4.17.0
Requires-Dist: pywin32>=307; platform_system == 'Windows'
Requires-Dist: pyyaml~=6.0
